PdeSimulation/__init__.py
PdeSimulation/burgers.py
PdeSimulation/heat_equation.py
PdeSimulation/transport_equation.py
PdeSimulation/wave_equation.py
pde_simulation/__init__.py
pde_simulation/burgers.py
pde_simulation/heat_equation.py
pde_simulation/transport_equation.py
pde_simulation/wave_equation.py
PdeSimulation-0.0.6.dist-info/METADATA
PdeSimulation-0.0.6.dist-info/WHEEL
PdeSimulation-0.0.6.dist-info/top_level.txt
PdeSimulation-0.0.6.dist-info/RECORD
