Metadata-Version: 2.1
Name: PdeSimulation
Version: 0.0.6
Summary: Numerical simulation of some PDEs using finite difference methods
Home-page: UNKNOWN
Author: Yun
License: UNKNOWN
Keywords: python,first package
Platform: UNKNOWN
Classifier: Development Status :: 3 - Alpha
Classifier: Intended Audience :: Education
Classifier: Programming Language :: Python :: 2
Classifier: Programming Language :: Python :: 3
Classifier: Operating System :: MacOS :: MacOS X
Classifier: Operating System :: Microsoft :: Windows
